vizual/__init__.py
vizual/client.py
vizual/server.py
vizual/vizual.py
vizual/static/index.html
vizual/static/assets/favicon.ico
vizual/static/assets/logo.png
vizual/static/css/index.css
vizual/static/uploads/example_fig.png
vizual-4.0.0.dist-info/LICENSE
vizual-4.0.0.dist-info/METADATA
vizual-4.0.0.dist-info/WHEEL
vizual-4.0.0.dist-info/entry_points.txt
vizual-4.0.0.dist-info/top_level.txt
vizual-4.0.0.dist-info/RECORD
