Metadata-Version: 2.1
Name: vizual
Version: 4.0.0
Summary: Web UI and decorator synatx for print statement debugging
Home-page: https://github.com/hugo1005/vizual
Author: Hugo Dolan
Author-email: <hugojdolan@gmail.com>
License: UNKNOWN
Download-URL: https://github.com/hugo1005/vizual/archive/refs/tags/v4.tar.gz
Keywords: python,debugging,webapp,visual
Platform: UNKNOWN
Classifier: Development Status :: 5 - Production/Stable
Classifier: Intended Audience :: Developers
Classifier: Programming Language :: Python :: 2
Classifier: Programming Language :: Python :: 3
Classifier: Operating System :: MacOS :: MacOS X
Classifier: Operating System :: Microsoft :: Windows
License-File: LICENSE
Requires-Dist: Flask
Requires-Dist: requests
Requires-Dist: docopt
Requires-Dist: pandas
Requires-Dist: numpy
